pvimage/__init__.py
pvimage/conf.py
pvimage/features.py
pvimage/learning.py
pvimage/pipelines.py
pvimage/process.py
pvimage/files/tutorials/full_module_processing.py
pvimage/files/tutorials/minimodule_processing.py
pvimage-0.0.10.dist-info/LICENSE
pvimage-0.0.10.dist-info/METADATA
pvimage-0.0.10.dist-info/WHEEL
pvimage-0.0.10.dist-info/top_level.txt
pvimage-0.0.10.dist-info/RECORD
