Metadata-Version: 2.1
Name: pvimage
Version: 0.0.10
Summary: PV EL Image Processing Tool
Author: Justin S. Fada, Nicholas A. Parrilla
Author-email: "Benjamin G. Pierce" <bgp12@case.edu>, Ahmad Maroof Karimi <karimiahmad@ornl.gov>, "Roger H. French" <rxf131@case.edu>, "Jennifer L. Braid" <jlbraid@sandia.gov>
License: 
Requires-Python: >=3.9
License-File: LICENSE
Requires-Dist: markdown
Requires-Dist: pandas
Requires-Dist: pyhull
Requires-Dist: opencv-python
Requires-Dist: scipy
Requires-Dist: scikit-image
Requires-Dist: glob2
Provides-Extra: test
Requires-Dist: pytest ; extra == 'test'
